astrolyze
astrolyze/functions
astrolyze/lte
astrolyze/maps
astrolyze/sed
astrolyze/spectra
