Metadata-Version: 1.1
Name: astrolyze
Version: 0.2.11
Summary: Reduction and analysing tools for (mainly)Radioastronomical Data.
Home-page: https://github.com/buchbend/astrolyze.git
Author: Christof Buchbender
Author-email: buchbend@ph1.uni-koeln.de
License: LICENSE.txt
Platform: UNKNOWN
Classifier: Intended Audience :: Science/Research
Classifier: Operating System :: POSIX :: Linux
Classifier: Programming Language :: Python :: 2.7
Classifier: Topic :: Scientific/Engineering :: Astronomy
Classifier: Topic :: Scientific/Engineering :: Physics
